predict_weather/__init__.py
predict_weather-0.0.1.dist-info/LICENSE.txt
predict_weather-0.0.1.dist-info/METADATA
predict_weather-0.0.1.dist-info/WHEEL
predict_weather-0.0.1.dist-info/top_level.txt
predict_weather-0.0.1.dist-info/RECORD
